napari_tomocube_data_viewer/__init__.py
napari_tomocube_data_viewer/_reader.py
napari_tomocube_data_viewer/napari.yaml
napari_tomocube_data_viewer/_tests/__init__.py
napari_tomocube_data_viewer/_tests/test_reader.py
napari_tomocube_data_viewer-2024.10.0.dist-info/LICENSE
napari_tomocube_data_viewer-2024.10.0.dist-info/METADATA
napari_tomocube_data_viewer-2024.10.0.dist-info/WHEEL
napari_tomocube_data_viewer-2024.10.0.dist-info/entry_points.txt
napari_tomocube_data_viewer-2024.10.0.dist-info/top_level.txt
napari_tomocube_data_viewer-2024.10.0.dist-info/RECORD
