Metadata-Version: 2.1
Name: napari-tomocube-data-viewer
Version: 2024.10.0
Summary: A plugin to visualize three-dimensional data from Tomocube's microscopy
Author-email: Dohyeon Lee <dleh428@kaist.ac.kr>
License: 
Project-URL: Bug Tracker, https://github.com/ehgus/napari-tomocube-data-viewer/issues
Project-URL: Documentation, https://github.com/ehgus/napari-tomocube-data-viewer
Project-URL: Source Code, https://github.com/ehgus/napari-tomocube-data-viewer
Project-URL: User Support, https://github.com/ehgus/napari-tomocube-data-viewer/issues
Classifier: Development Status :: 2 - Pre-Alpha
Classifier: Framework :: napari
Classifier: Intended Audience :: Developers
Classifier: License :: OSI Approved :: MIT License
Classifier: Operating System :: OS Independent
Classifier: Programming Language :: Python
Classifier: Programming Language :: Python :: 3
Classifier: Programming Language :: Python :: 3 :: Only
Classifier: Programming Language :: Python :: 3.8
Classifier: Programming Language :: Python :: 3.9
Classifier: Programming Language :: Python :: 3.10
Classifier: Programming Language :: Python :: 3.11
Classifier: Programming Language :: Python :: 3.12
Classifier: Topic :: Scientific/Engineering :: Image Processing
Requires-Python: >=3.8
License-File: LICENSE
Requires-Dist: numpy
Requires-Dist: TCFile>=2024.10.1
Provides-Extra: testing
Requires-Dist: tox; extra == "testing"
Requires-Dist: pytest; extra == "testing"
Requires-Dist: pytest-cov; extra == "testing"
